djwalebabu/__init__.py
djwalebabu/__main__.py
djwalebabu-0.0.2.dist-info/LICENSE
djwalebabu-0.0.2.dist-info/METADATA
djwalebabu-0.0.2.dist-info/WHEEL
djwalebabu-0.0.2.dist-info/top_level.txt
djwalebabu-0.0.2.dist-info/RECORD
