Metadata-Version: 2.1
Name: djwalebabu
Version: 0.0.2
Summary: A demonstration library to show how package distribution works in python
Author: Hargun Oberoi
Author-email: hargun3045@gmail.com
License: UNKNOWN
Keywords: pyds,ai0,hargun,oberoi,djwalebabu
Platform: UNKNOWN
Classifier: Programming Language :: Python :: 3
Classifier: License :: OSI Approved :: MIT License
Classifier: Operating System :: OS Independent
Requires-Python: >=3.6
License-File: LICENSE
